kracked/kraken_test.py
kracked/kraken_tick.py
kracked-0.0.1.dist-info/LICENSE
kracked-0.0.1.dist-info/METADATA
kracked-0.0.1.dist-info/WHEEL
kracked-0.0.1.dist-info/entry_points.txt
kracked-0.0.1.dist-info/top_level.txt
kracked-0.0.1.dist-info/RECORD
