Metadata-Version: 2.1
Name: kracked
Version: 0.0.1
Summary: TBA
Author-email: Robert Stanton <robertmstanton@proton.me>
Maintainer-email: Robert Stanton <robertmstanton@proton.me>
Project-URL: Homepage, https://github.com/r2stanton/kracked
Project-URL: Bug Reports, https://github.com/r2stanton/kracked/issues
Keywords: TBA
Classifier: Development Status :: 3 - Alpha
Classifier: Intended Audience :: Developers
Classifier: Topic :: Software Development :: Build Tools
Classifier: License :: OSI Approved :: MIT License
Classifier: Programming Language :: Python :: 3.10
Classifier: Programming Language :: Python :: 3.11
Classifier: Programming Language :: Python :: 3.12
Classifier: Programming Language :: Python :: 3 :: Only
Requires-Python: >=3.10
License-File: LICENSE
Provides-Extra: dev
Requires-Dist: check-manifest ; extra == 'dev'
Provides-Extra: test
Requires-Dist: coverage ; extra == 'test'
